[
    {
        "item": "Blouse",
        "insight": "Customers who bought Blouse in Spring rated it 3.7\u2605 \u2014 18% were Delighted, making it a bottom performer in the Clothing category."
    },
    {
        "item": "Pants",
        "insight": "Customers who bought Pants in Winter rated it 3.7\u2605 \u2014 22% were Delighted, making it a bottom performer in the Clothing category."
    },
    {
        "item": "Jewelry",
        "insight": "Customers who bought Jewelry in Summer rated it 3.8\u2605 \u2014 22% were Delighted, making it a solid performer in the Accessories category."
    },
    {
        "item": "Shirt",
        "insight": "Customers who bought Shirt in Winter rated it 3.6\u2605 \u2014 18% were Delighted, making it a bottom performer in the Clothing category."
    },
    {
        "item": "Dress",
        "insight": "Customers who bought Dress in Summer rated it 3.8\u2605 \u2014 22% were Delighted, making it a solid performer in the Clothing category."
    },
    {
        "item": "Sweater",
        "insight": "Customers who bought Sweater in Spring rated it 3.8\u2605 \u2014 23% were Delighted, making it a solid performer in the Clothing category."
    },
    {
        "item": "Jacket",
        "insight": "Customers who bought Jacket in Fall rated it 3.8\u2605 \u2014 18% were Delighted, making it a solid performer in the Outerwear category."
    },
    {
        "item": "Coat",
        "insight": "Customers who bought Coat in Spring rated it 3.7\u2605 \u2014 17% were Delighted, making it a solid performer in the Outerwear category."
    },
    {
        "item": "Sunglasses",
        "insight": "Customers who bought Sunglasses in Winter rated it 3.7\u2605 \u2014 22% were Delighted, making it a solid performer in the Accessories category."
    },
    {
        "item": "Belt",
        "insight": "Customers who bought Belt in Fall rated it 3.8\u2605 \u2014 24% were Delighted, making it a solid performer in the Accessories category."
    },
    {
        "item": "Sandals",
        "insight": "Customers who bought Sandals in Fall rated it 3.8\u2605 \u2014 27% were Delighted, making it a top performer in the Footwear category."
    },
    {
        "item": "Socks",
        "insight": "Customers who bought Socks in Fall rated it 3.8\u2605 \u2014 23% were Delighted, making it a solid performer in the Clothing category."
    },
    {
        "item": "Skirt",
        "insight": "Customers who bought Skirt in Fall rated it 3.8\u2605 \u2014 20% were Delighted, making it a top performer in the Clothing category."
    },
    {
        "item": "Scarf",
        "insight": "Customers who bought Scarf in Summer rated it 3.7\u2605 \u2014 23% were Delighted, making it a bottom performer in the Accessories category."
    },
    {
        "item": "Shorts",
        "insight": "Customers who bought Shorts in Spring rated it 3.7\u2605 \u2014 19% were Delighted, making it a bottom performer in the Clothing category."
    },
    {
        "item": "Hat",
        "insight": "Customers who bought Hat in Fall rated it 3.8\u2605 \u2014 21% were Delighted, making it a top performer in the Accessories category."
    },
    {
        "item": "Handbag",
        "insight": "Customers who bought Handbag in Fall rated it 3.8\u2605 \u2014 22% were Delighted, making it a top performer in the Accessories category."
    },
    {
        "item": "Hoodie",
        "insight": "Customers who bought Hoodie in Winter rated it 3.7\u2605 \u2014 21% were Delighted, making it a bottom performer in the Clothing category."
    },
    {
        "item": "Shoes",
        "insight": "Customers who bought Shoes in Summer rated it 3.7\u2605 \u2014 22% were Delighted, making it a solid performer in the Footwear category."
    },
    {
        "item": "T-shirt",
        "insight": "Customers who bought T-shirt in Winter rated it 3.8\u2605 \u2014 24% were Delighted, making it a top performer in the Clothing category."
    },
    {
        "item": "Sneakers",
        "insight": "Customers who bought Sneakers in Spring rated it 3.8\u2605 \u2014 20% were Delighted, making it a solid performer in the Footwear category."
    },
    {
        "item": "Boots",
        "insight": "Customers who bought Boots in Spring rated it 3.8\u2605 \u2014 24% were Delighted, making it a top performer in the Footwear category."
    },
    {
        "item": "Backpack",
        "insight": "Customers who bought Backpack in Summer rated it 3.8\u2605 \u2014 24% were Delighted, making it a solid performer in the Accessories category."
    },
    {
        "item": "Gloves",
        "insight": "Customers who bought Gloves in Spring rated it 3.9\u2605 \u2014 27% were Delighted, making it a top performer in the Accessories category."
    },
    {
        "item": "Jeans",
        "insight": "Customers who bought Jeans in Fall rated it 3.6\u2605 \u2014 17% were Delighted, making it a bottom performer in the Clothing category."
    }
]